design.sv
// design.sv
module BCD(clk, rst_asyn, Q_out);
input clk; 
input rst_asyn; 
output [3:0] Q_out; 
reg [3:0] Q_out;
    always@ (posedge clk or posedge rst_asyn)
        begin
            if (rst_asyn)
                Q_out=0;
            else if (Q_out == 9)
                Q_out=0;
            else
                Q_out=Q_out+1;
        end
endmodule

testbench.sv
// testbench
module BCD_Counter_tb;
reg clk,rst_asyn;    
wire [3:0] Q_out;   
initial begin
    #0;
    forever
    begin
        clk = 1'b0;
        #5 clk = 1'b1;
        #5;
    end
end
initial begin
    #0 rst_asyn=1'b1;   
    #5 rst_asyn=1'b0;
    #44 rst_asyn=1'b1;  
    #1 rst_asyn=1'b0;
    #150 $finish;
end
BCD BCD_Counter_tb(.clk(clk), .rst_asyn(rst_asyn), .Q_out(Q_out));
initial begin
    $dumpfile("BCD_Counter.vcd");
    $dumpvars(0, BCD_Counter_tb);
end
endmodule

BCD_Counter.vcd
$date
	Sun May  1 14:00:35 2022
$end
$version
	Icarus Verilog
$end
$timescale
	1s
$end
$scope module BCD_Counter_tb $end
$scope module BCD_Counter_tb $end
$var wire 1 ! clk $end
$var wire 1 " rst_asyn $end
$var reg 4 # Q_out [3:0] $end
$upscope $end
$upscope $end
$enddefinitions $end
#0
$dumpvars
b0 #
1"
0!
$end
#5
b1 #
0"
1!
#10
0!
#15
b10 #
1!
#20
0!
#25
b11 #
1!
#30
0!
#35
b100 #
1!
#40
0!
#45
b101 #
1!
#49
b0 #
1"
#50
0"
0!
#55
b1 #
1!
#60
0!
#65
b10 #
1!
#70
0!
#75
b11 #
1!
#80
0!
#85
b100 #
1!
#90
0!
#95
b101 #
1!
#100
0!
#105
b110 #
1!
#110
0!
#115
b111 #
1!
#120
0!
#125
b1000 #
1!
#130
0!
#135
b1001 #
1!
#140
0!
#145
b0 #
1!
#150
0!
#155
b1 #
1!
#160
0!
#165
b10 #
1!
#170
0!
#175
b11 #
1!
#180
0!
#185
b100 #
1!
#190
0!
#195
b101 #
1!
